pathpretrain/__init__.py
pathpretrain/datasets.py
pathpretrain/embed.py
pathpretrain/models.py
pathpretrain/predict.py
pathpretrain/preprocess.py
pathpretrain/process_xml.py
pathpretrain/schedulers.py
pathpretrain/train_model.py
pathpretrain/utils.py
pathpretrain-0.1.2.dist-info/LICENSE
pathpretrain-0.1.2.dist-info/METADATA
pathpretrain-0.1.2.dist-info/WHEEL
pathpretrain-0.1.2.dist-info/entry_points.txt
pathpretrain-0.1.2.dist-info/top_level.txt
pathpretrain-0.1.2.dist-info/RECORD
